{"settings":{"dingtalk_webhook":"https://oapi.dingtalk.com/robot/send?access_token=ea508357bbcd5c6801fa5cb91bf0dc9126c4f2c04f5a64bbd2fdae690f0bc56f","dingtalk_secret":"SEC094d44544892fcdc78bd5283c85dea129475cd785d9851bf12e0c65420a378b0","dingtalk_at_user_ids":[],"notification_targets":[{"name":"默认机器人","webhook":"https://oapi.dingtalk.com/robot/send?access_token=ea508357bbcd5c6801fa5cb91bf0dc9126c4f2c04f5a64bbd2fdae690f0bc56f","secret":"SEC094d44544892fcdc78bd5283c85dea129475cd785d9851bf12e0c65420a378b0","enabled":true}],"premium_threshold":20.0,"poll_interval_seconds":60,"alert_cooldown_seconds":900,"request_timeout_seconds":10.0,"reversal_cooldown_seconds":1800,"reversal_price_lookback_minutes":60,"reversal_price_rebound_pct":1.2,"reversal_price_ma_window":15,"reversal_signal_window_minutes":180,"us10y_poll_interval_seconds":60,"us10y_drop_lookback_hours":24.0,"us10y_drop_threshold_bp":1.0,"us10y_tenors":["10y"],"rss_poll_interval_seconds":1800,"rss_feed_urls":["https://rss.huxiu.com/","https://quanwenrss.com/bloomberg/economics","http://rss.jintiankansha.me/rss/GM3DSNZUGJ6DOYTEG5RWENZRGUZDENLDGAYGMMDGMRSTONBRMUYWMM3FMQ2DGYZXMZSTGNDGG4YQ====","https://rss.beehiiv.com/feeds/4aF2pGVAEN.xml","http://rss.jintiankansha.me/rss/GM4DKMRUG56DIYZTHE2TAY3EGNTDAMLGMQZWKMRRGNRWCZBQMY2TSZLEGEYTQN3DMQYDSNZUGQYA====","http://rss.jintiankansha.me/rss/GM3DSNZUGJ6DOYTEG5RWENZRGUZDENLDGAYGMMDGMRSTONBRMUYWMM3FMQ2DGYZXMZSTGNDGG4YQ===="]},"market_state":{"sge":{"active":true,"label":"运行中","detail":"国内金或国际金有可用价格源"},"reversal":{"active":true,"label":"运行中","detail":"黄金盘面监控可用"},"us10y":{"active":true,"label":"可用","detail":"十年期美债数据源可用（Sina优先，FRED回退）"},"rss":{"active":true,"label":"可用","detail":"RSS 手动抓取和定时抓取配置可用"}},"latest_sample":{"id":4631,"fetched_at":"2026-03-25T15:34:35.131468+08:00","shfe_price_cny_per_g":1013.2728,"london_price_usd_per_oz":4554.97,"usdcny_rate":6.8953,"london_price_cny_per_g":1009.7869,"premium_cny_per_g":3.4859,"poll_interval_seconds":60,"both_markets_open":0,"shfe_market_open":0,"london_market_open":1,"alert_triggered":0,"raw_payload":"var hq_str_nf_AU0=\"黄金连续,150000,977.000,1027.880,970.260,1013.960,1013.860,1013.960,1013.960,998.740,979.240,1,51,169532.000,317182,沪,黄金,2026-03-25,1,,,,,,,,,998.742,0.000,0,0.000,0,0.000,0,0.000,0,0.000,0,0.000,0,0.000,0,0.000,0\";\nvar hq_str_gds_AU9999=\"1015.50,0,1015.00,1015.50,1028.99,965.10,15:29:59,979.56,980.00,1354300,20.00,154.00,2026-03-25,沪金99\";\nvar hq_str_gds_AUTD=\"1013.51,0,1013.51,1014.79,1024.00,967.50,15:29:54,977.99,977.00,80426,4.00,2.00,2026-03-25,黄金延期\";\nvar hq_str_hf_XAU=\"4554.97,4474.260,4554.97,4555.32,4602.10,4455.98,15:34:00,4474.26,4475.66,0,0,0,2026-03-25,伦敦金（现货黄金）\";\nvar hq_str_hf_GC=\"4591.458,,4585.900,4586.300,4634.000,4491.700,15:34:08,4434.100,4506.100,0,2,1,2026-03-25,纽约黄金,0\";\nvar hq_str_USDCNY=\"15:33:47,6.8953,6.8975,6.8913,150,6.8913,6.8965,6.8815,6.8964,美元人民币,2026-03-25\";","note":"国内源: 代理人民币金价(基于最近有效样本比例，参考 03-25 15:33)；国际源: 新浪 hf_XAU 伦敦金现货"},"recent_alerts":[],"recent_fetch_runs":[{"id":4665,"fetched_at":"2026-03-25T15:34:35.131468+08:00","success":1,"poll_interval_seconds":60,"duration_ms":556,"error_message":null},{"id":4664,"fetched_at":"2026-03-25T15:33:35.139118+08:00","success":1,"poll_interval_seconds":60,"duration_ms":544,"error_message":null},{"id":4663,"fetched_at":"2026-03-25T15:32:35.144255+08:00","success":1,"poll_interval_seconds":60,"duration_ms":549,"error_message":null},{"id":4662,"fetched_at":"2026-03-25T15:31:35.124518+08:00","success":1,"poll_interval_seconds":60,"duration_ms":699,"error_message":null},{"id":4661,"fetched_at":"2026-03-25T15:30:35.126281+08:00","success":1,"poll_interval_seconds":60,"duration_ms":712,"error_message":null},{"id":4660,"fetched_at":"2026-03-25T15:29:35.176004+08:00","success":1,"poll_interval_seconds":60,"duration_ms":676,"error_message":null},{"id":4659,"fetched_at":"2026-03-25T15:28:35.136094+08:00","success":1,"poll_interval_seconds":60,"duration_ms":693,"error_message":null},{"id":4658,"fetched_at":"2026-03-25T15:27:35.131198+08:00","success":1,"poll_interval_seconds":60,"duration_ms":532,"error_message":null},{"id":4657,"fetched_at":"2026-03-25T15:26:35.142101+08:00","success":1,"poll_interval_seconds":60,"duration_ms":686,"error_message":null},{"id":4656,"fetched_at":"2026-03-25T15:25:35.137777+08:00","success":1,"poll_interval_seconds":60,"duration_ms":827,"error_message":null}],"recent_samples":[{"id":4631,"fetched_at":"2026-03-25T15:34:35.131468+08:00","shfe_price_cny_per_g":1013.2728,"london_price_usd_per_oz":4554.97,"usdcny_rate":6.8953,"london_price_cny_per_g":1009.7869,"premium_cny_per_g":3.4859,"poll_interval_seconds":60,"both_markets_open":0,"shfe_market_open":0,"london_market_open":1,"alert_triggered":0,"raw_payload":"var hq_str_nf_AU0=\"黄金连续,150000,977.000,1027.880,970.260,1013.960,1013.860,1013.960,1013.960,998.740,979.240,1,51,169532.000,317182,沪,黄金,2026-03-25,1,,,,,,,,,998.742,0.000,0,0.000,0,0.000,0,0.000,0,0.000,0,0.000,0,0.000,0,0.000,0\";\nvar hq_str_gds_AU9999=\"1015.50,0,1015.00,1015.50,1028.99,965.10,15:29:59,979.56,980.00,1354300,20.00,154.00,2026-03-25,沪金99\";\nvar hq_str_gds_AUTD=\"1013.51,0,1013.51,1014.79,1024.00,967.50,15:29:54,977.99,977.00,80426,4.00,2.00,2026-03-25,黄金延期\";\nvar hq_str_hf_XAU=\"4554.97,4474.260,4554.97,4555.32,4602.10,4455.98,15:34:00,4474.26,4475.66,0,0,0,2026-03-25,伦敦金（现货黄金）\";\nvar hq_str_hf_GC=\"4591.458,,4585.900,4586.300,4634.000,4491.700,15:34:08,4434.100,4506.100,0,2,1,2026-03-25,纽约黄金,0\";\nvar hq_str_USDCNY=\"15:33:47,6.8953,6.8975,6.8913,150,6.8913,6.8965,6.8815,6.8964,美元人民币,2026-03-25\";","note":"国内源: 代理人民币金价(基于最近有效样本比例，参考 03-25 15:33)；国际源: 新浪 hf_XAU 伦敦金现货"},{"id":4630,"fetched_at":"2026-03-25T15:33:35.139118+08:00","shfe_price_cny_per_g":1013.349,"london_price_usd_per_oz":4554.19,"usdcny_rate":6.897,"london_price_cny_per_g":1009.8629,"premium_cny_per_g":3.4861,"poll_interval_seconds":60,"both_markets_open":0,"shfe_market_open":0,"london_market_open":1,"alert_triggered":0,"raw_payload":"var hq_str_nf_AU0=\"黄金连续,150000,977.000,1027.880,970.260,1013.960,1013.860,1013.960,1013.960,998.740,979.240,1,51,169532.000,317182,沪,黄金,2026-03-25,1,,,,,,,,,998.742,0.000,0,0.000,0,0.000,0,0.000,0,0.000,0,0.000,0,0.000,0,0.000,0\";\nvar hq_str_gds_AU9999=\"1015.50,0,1015.00,1015.50,1028.99,965.10,15:29:59,979.56,980.00,1354300,20.00,154.00,2026-03-25,沪金99\";\nvar hq_str_gds_AUTD=\"1013.51,0,1013.51,1014.79,1024.00,967.50,15:29:54,977.99,977.00,80426,4.00,2.00,2026-03-25,黄金延期\";\nvar hq_str_hf_XAU=\"4554.19,4474.260,4554.19,4554.54,4602.10,4455.98,15:33:00,4474.26,4475.66,0,0,0,2026-03-25,伦敦金（现货黄金）\";\nvar hq_str_hf_GC=\"4591.404,,4587.400,4587.900,4634.000,4491.700,15:33:18,4434.100,4506.100,0,4,4,2026-03-25,纽约黄金,0\";\nvar hq_str_USDCNY=\"15:33:02,6.8970,6.8974,6.8860,162,6.8887,6.9001,6.8839,6.9001,美元人民币,2026-03-25\";","note":"国内源: 代理人民币金价(基于最近有效样本比例，参考 03-25 15:32)；国际源: 新浪 hf_XAU 伦敦金现货"},{"id":4629,"fetched_at":"2026-03-25T15:32:35.144255+08:00","shfe_price_cny_per_g":1013.157,"london_price_usd_per_oz":4554.78,"usdcny_rate":6.8948,"london_price_cny_per_g":1009.6716,"premium_cny_per_g":3.4854,"poll_interval_seconds":60,"both_markets_open":0,"shfe_market_open":0,"london_market_open":1,"alert_triggered":0,"raw_payload":"var hq_str_nf_AU0=\"黄金连续,150000,977.000,1027.880,970.260,1013.960,1013.860,1013.960,1013.960,998.740,979.240,1,51,169532.000,317182,沪,黄金,2026-03-25,1,,,,,,,,,998.742,0.000,0,0.000,0,0.000,0,0.000,0,0.000,0,0.000,0,0.000,0,0.000,0\";\nvar hq_str_gds_AU9999=\"1015.50,0,1015.00,1015.50,1028.99,965.10,15:29:59,979.56,980.00,1354300,20.00,154.00,2026-03-25,沪金99\";\nvar hq_str_gds_AUTD=\"1013.51,0,1013.51,1014.79,1024.00,967.50,15:29:54,977.99,977.00,80426,4.00,2.00,2026-03-25,黄金延期\";\nvar hq_str_hf_XAU=\"4554.78,4474.260,4554.78,4555.13,4602.10,4455.98,15:32:00,4474.26,4475.66,0,0,0,2026-03-25,伦敦金（现货黄金）\";\nvar hq_str_hf_GC=\"4591.903,,4586.100,4586.700,4634.000,4491.700,15:32:11,4434.100,4506.100,0,1,1,2026-03-25,纽约黄金,0\";\nvar hq_str_USDCNY=\"15:31:43,6.8948,6.8970,6.8913,150,6.8913,6.8965,6.8815,6.8959,美元人民币,2026-03-25\";","note":"国内源: 代理人民币金价(基于最近有效样本比例，参考 03-25 15:31)；国际源: 新浪 hf_XAU 伦敦金现货"},{"id":4628,"fetched_at":"2026-03-25T15:31:35.124518+08:00","shfe_price_cny_per_g":1013.2579,"london_price_usd_per_oz":4555.3,"usdcny_rate":6.8947,"london_price_cny_per_g":1009.7722,"premium_cny_per_g":3.4857,"poll_interval_seconds":60,"both_markets_open":0,"shfe_market_open":0,"london_market_open":1,"alert_triggered":0,"raw_payload":"var hq_str_nf_AU0=\"黄金连续,150000,977.000,1027.880,970.260,1013.960,1013.860,1013.960,1013.960,998.740,979.240,1,51,169532.000,317182,沪,黄金,2026-03-25,1,,,,,,,,,998.742,0.000,0,0.000,0,0.000,0,0.000,0,0.000,0,0.000,0,0.000,0,0.000,0\";\nvar hq_str_gds_AU9999=\"1015.50,0,1015.00,1015.50,1028.99,965.10,15:29:59,979.56,980.00,1354300,20.00,154.00,2026-03-25,沪金99\";\nvar hq_str_gds_AUTD=\"1013.51,0,1013.51,1014.79,1024.00,967.50,15:29:54,977.99,977.00,80426,4.00,2.00,2026-03-25,黄金延期\";\nvar hq_str_hf_XAU=\"4555.30,4474.260,4555.30,4555.65,4602.10,4455.98,15:31:00,4474.26,4475.66,0,0,0,2026-03-25,伦敦金（现货黄金）\";\nvar hq_str_hf_GC=\"4592.170,,4586.200,4586.800,4634.000,4491.700,15:31:23,4434.100,4506.100,0,2,1,2026-03-25,纽约黄金,0\";\nvar hq_str_USDCNY=\"15:30:46,6.8947,6.8967,6.8913,150,6.8913,6.8965,6.8815,6.8957,美元人民币,2026-03-25\";","note":"国内源: 代理人民币金价(基于最近有效样本比例，参考 03-25 15:30)；国际源: 新浪 hf_XAU 伦敦金现货"},{"id":4627,"fetched_at":"2026-03-25T15:30:35.126281+08:00","shfe_price_cny_per_g":1014.3764,"london_price_usd_per_oz":4560.13,"usdcny_rate":6.895,"london_price_cny_per_g":1010.8869,"premium_cny_per_g":3.4895,"poll_interval_seconds":60,"both_markets_open":0,"shfe_market_open":0,"london_market_open":1,"alert_triggered":0,"raw_payload":"var hq_str_nf_AU0=\"黄金连续,150000,977.000,1027.880,970.260,1013.960,1013.860,1013.960,1013.960,998.740,979.240,1,51,169532.000,317182,沪,黄金,2026-03-25,1,,,,,,,,,998.742,0.000,0,0.000,0,0.000,0,0.000,0,0.000,0,0.000,0,0.000,0,0.000,0\";\nvar hq_str_gds_AU9999=\"1015.50,0,1015.00,1015.50,1028.99,965.10,15:29:59,979.56,980.00,1354300,20.00,154.00,2026-03-25,沪金99\";\nvar hq_str_gds_AUTD=\"1013.51,0,1013.51,1014.79,1024.00,967.50,15:29:54,977.99,977.00,80426,4.00,2.00,2026-03-25,黄金延期\";\nvar hq_str_hf_XAU=\"4560.13,4474.260,4560.13,4560.48,4602.10,4455.98,15:30:00,4474.26,4475.66,0,0,0,2026-03-25,伦敦金（现货黄金）\";\nvar hq_str_hf_GC=\"4592.876,,4588.800,4589.300,4634.000,4491.700,15:30:25,4434.100,4506.100,0,1,2,2026-03-25,纽约黄金,0\";\nvar hq_str_USDCNY=\"15:29:45,6.8950,6.8970,6.8913,150,6.8913,6.8965,6.8815,6.8960,美元人民币,2026-03-25\";","note":"国内源: 代理人民币金价(基于最近有效样本比例，参考 03-25 15:29)；国际源: 新浪 hf_XAU 伦敦金现货"},{"id":4626,"fetched_at":"2026-03-25T15:29:35.176004+08:00","shfe_price_cny_per_g":1013.9403,"london_price_usd_per_oz":4558.5,"usdcny_rate":6.8945,"london_price_cny_per_g":1010.4523,"premium_cny_per_g":3.488,"poll_interval_seconds":60,"both_markets_open":0,"shfe_market_open":0,"london_market_open":1,"alert_triggered":0,"raw_payload":"var hq_str_nf_AU0=\"黄金连续,150000,977.000,1027.880,970.260,1013.960,1013.860,1013.960,1013.960,998.740,979.240,1,51,169532.000,317182,沪,黄金,2026-03-25,1,,,,,,,,,998.742,0.000,0,0.000,0,0.000,0,0.000,0,0.000,0,0.000,0,0.000,0,0.000,0\";\nvar hq_str_gds_AU9999=\"1015.50,0,1015.50,1016.00,1028.99,965.10,15:29:09,979.56,980.00,1349600,56.00,4.00,2026-03-25,沪金99\";\nvar hq_str_gds_AUTD=\"1014.80,0,1014.55,1014.80,1024.00,967.50,15:29:09,977.99,977.00,80340,3.00,6.00,2026-03-25,黄金延期\";\nvar hq_str_hf_XAU=\"4558.50,4474.260,4558.50,4558.85,4602.10,4455.98,15:29:00,4474.26,4475.66,0,0,0,2026-03-25,伦敦金（现货黄金）\";\nvar hq_str_hf_GC=\"4595.120,,4590.500,4591.100,4634.000,4491.700,15:29:21,4434.100,4506.100,0,4,2,2026-03-25,纽约黄金,0\";\nvar hq_str_USDCNY=\"15:29:05,6.8945,6.8967,6.8913,150,6.8913,6.8965,6.8815,6.8956,美元人民币,2026-03-25\";","note":"国内源: 代理人民币金价(基于最近有效样本比例，参考 03-25 15:28)；国际源: 新浪 hf_XAU 伦敦金现货"},{"id":4625,"fetched_at":"2026-03-25T15:28:35.136094+08:00","shfe_price_cny_per_g":1014.3251,"london_price_usd_per_oz":4560.23,"usdcny_rate":6.8945,"london_price_cny_per_g":1010.8357,"premium_cny_per_g":3.4894,"poll_interval_seconds":60,"both_markets_open":0,"shfe_market_open":0,"london_market_open":1,"alert_triggered":0,"raw_payload":"var hq_str_nf_AU0=\"黄金连续,150000,977.000,1027.880,970.260,1013.960,1013.860,1013.960,1013.960,998.740,979.240,1,51,169532.000,317182,沪,黄金,2026-03-25,1,,,,,,,,,998.742,0.000,0,0.000,0,0.000,0,0.000,0,0.000,0,0.000,0,0.000,0,0.000,0\";\nvar hq_str_gds_AU9999=\"1015.50,0,1015.00,1015.50,1028.99,965.10,15:28:10,979.56,980.00,1345600,1.00,4.00,2026-03-25,沪金99\";\nvar hq_str_gds_AUTD=\"1014.02,0,1014.90,1015.19,1024.00,967.50,15:28:09,977.99,977.00,80246,1.00,1.00,2026-03-25,黄金延期\";\nvar hq_str_hf_XAU=\"4560.23,4474.260,4560.23,4560.58,4602.10,4455.98,15:28:00,4474.26,4475.66,0,0,0,2026-03-25,伦敦金（现货黄金）\";\nvar hq_str_hf_GC=\"4595.750,,4591.000,4591.400,4634.000,4491.700,15:28:24,4434.100,4506.100,0,1,1,2026-03-25,纽约黄金,0\";\nvar hq_str_USDCNY=\"15:27:43,6.8945,6.8963,6.8913,150,6.8913,6.8965,6.8815,6.8954,美元人民币,2026-03-25\";","note":"国内源: 代理人民币金价(基于最近有效样本比例，参考 03-25 15:27)；国际源: 新浪 hf_XAU 伦敦金现货"},{"id":4624,"fetched_at":"2026-03-25T15:27:35.131198+08:00","shfe_price_cny_per_g":1014.8189,"london_price_usd_per_oz":4562.45,"usdcny_rate":6.8945,"london_price_cny_per_g":1011.3278,"premium_cny_per_g":3.4911,"poll_interval_seconds":60,"both_markets_open":0,"shfe_market_open":0,"london_market_open":1,"alert_triggered":0,"raw_payload":"var hq_str_nf_AU0=\"黄金连续,150000,977.000,1027.880,970.260,1013.960,1013.860,1013.960,1013.960,998.740,979.240,1,51,169532.000,317182,沪,黄金,2026-03-25,1,,,,,,,,,998.742,0.000,0,0.000,0,0.000,0,0.000,0,0.000,0,0.000,0,0.000,0,0.000,0\";\nvar hq_str_gds_AU9999=\"1014.50,0,1014.50,1015.00,1028.99,965.10,15:27:07,979.56,980.00,1345600,66.00,7.00,2026-03-25,沪金99\";\nvar hq_str_gds_AUTD=\"1015.00,0,1014.70,1015.00,1024.00,967.50,15:27:10,977.99,977.00,80200,3.00,1.00,2026-03-25,黄金延期\";\nvar hq_str_hf_XAU=\"4562.45,4474.260,4562.45,4562.80,4602.10,4455.98,15:27:00,4474.26,4475.66,0,0,0,2026-03-25,伦敦金（现货黄金）\";\nvar hq_str_hf_GC=\"4597.236,,4592.900,4593.400,4634.000,4491.700,15:27:26,4434.100,4506.100,0,1,1,2026-03-25,纽约黄金,0\";\nvar hq_str_USDCNY=\"15:26:34,6.8945,6.8955,6.8913,150,6.8913,6.8965,6.8815,6.8950,美元人民币,2026-03-25\";","note":"国内源: 代理人民币金价(基于最近有效样本比例，参考 03-25 15:26)；国际源: 新浪 hf_XAU 伦敦金现货"},{"id":4623,"fetched_at":"2026-03-25T15:26:35.142101+08:00","shfe_price_cny_per_g":1013.8758,"london_price_usd_per_oz":4558.21,"usdcny_rate":6.8945,"london_price_cny_per_g":1010.388,"premium_cny_per_g":3.4878,"poll_interval_seconds":60,"both_markets_open":0,"shfe_market_open":0,"london_market_open":1,"alert_triggered":0,"raw_payload":"var hq_str_nf_AU0=\"黄金连续,150000,977.000,1027.880,970.260,1013.960,1013.860,1013.960,1013.960,998.740,979.240,1,51,169532.000,317182,沪,黄金,2026-03-25,1,,,,,,,,,998.742,0.000,0,0.000,0,0.000,0,0.000,0,0.000,0,0.000,0,0.000,0,0.000,0\";\nvar hq_str_gds_AU9999=\"1014.01,0,1014.31,1015.00,1028.99,965.10,15:25:56,979.56,980.00,1345300,8.00,110.00,2026-03-25,沪金99\";\nvar hq_str_gds_AUTD=\"1014.00,0,1014.01,1014.28,1024.00,967.50,15:26:09,977.99,977.00,80160,2.00,6.00,2026-03-25,黄金延期\";\nvar hq_str_hf_XAU=\"4558.21,4474.260,4558.21,4558.56,4602.10,4455.98,15:26:00,4474.26,4475.66,0,0,0,2026-03-25,伦敦金（现货黄金）\";\nvar hq_str_hf_GC=\"4593.612,,4590.000,4590.500,4634.000,4491.700,15:26:25,4434.100,4506.100,0,2,4,2026-03-25,纽约黄金,0\";\nvar hq_str_USDCNY=\"15:26:04,6.8945,6.8955,6.8913,150,6.8913,6.8965,6.8815,6.8950,美元人民币,2026-03-25\";","note":"国内源: 代理人民币金价(基于最近有效样本比例，参考 03-25 15:25)；国际源: 新浪 hf_XAU 伦敦金现货"},{"id":4622,"fetched_at":"2026-03-25T15:25:35.137777+08:00","shfe_price_cny_per_g":1013.5771,"london_price_usd_per_oz":4557.33,"usdcny_rate":6.8938,"london_price_cny_per_g":1010.0903,"premium_cny_per_g":3.4868,"poll_interval_seconds":60,"both_markets_open":0,"shfe_market_open":0,"london_market_open":1,"alert_triggered":0,"raw_payload":"var hq_str_nf_AU0=\"黄金连续,150000,977.000,1027.880,970.260,1013.960,1013.860,1013.960,1013.960,998.740,979.240,1,51,169532.000,317182,沪,黄金,2026-03-25,1,,,,,,,,,998.742,0.000,0,0.000,0,0.000,0,0.000,0,0.000,0,0.000,0,0.000,0,0.000,0\";\nvar hq_str_gds_AU9999=\"1013.51,0,1013.50,1014.01,1028.99,965.10,15:25:10,979.56,980.00,1344700,3.00,10.00,2026-03-25,沪金99\";\nvar hq_str_gds_AUTD=\"1013.94,0,1013.70,1014.19,1024.00,967.50,15:25:10,977.99,977.00,80112,1.00,1.00,2026-03-25,黄金延期\";\nvar hq_str_hf_XAU=\"4557.33,4474.260,4557.33,4557.68,4602.10,4455.98,15:25:00,4474.26,4475.66,0,0,0,2026-03-25,伦敦金（现货黄金）\";\nvar hq_str_hf_GC=\"4591.956,,4588.400,4588.700,4634.000,4491.700,15:25:20,4434.100,4506.100,0,1,1,2026-03-25,纽约黄金,0\";\nvar hq_str_USDCNY=\"15:24:31,6.8938,6.8948,6.8913,150,6.8913,6.8965,6.8815,6.8943,美元人民币,2026-03-25\";","note":"国内源: 代理人民币金价(基于最近有效样本比例，参考 03-25 15:24)；国际源: 新浪 hf_XAU 伦敦金现货"},{"id":4621,"fetched_at":"2026-03-25T15:24:35.141862+08:00","shfe_price_cny_per_g":1013.7617,"london_price_usd_per_oz":4558.16,"usdcny_rate":6.8938,"london_price_cny_per_g":1010.2743,"premium_cny_per_g":3.4874,"poll_interval_seconds":60,"both_markets_open":0,"shfe_market_open":0,"london_market_open":1,"alert_triggered":0,"raw_payload":"var hq_str_nf_AU0=\"黄金连续,150000,977.000,1027.880,970.260,1013.960,1013.860,1013.960,1013.960,998.740,979.240,1,51,169532.000,317182,沪,黄金,2026-03-25,1,,,,,,,,,998.742,0.000,0,0.000,0,0.000,0,0.000,0,0.000,0,0.000,0,0.000,0,0.000,0\";\nvar hq_str_gds_AU9999=\"1013.51,0,1013.51,1014.01,1028.99,965.10,15:24:08,979.56,980.00,1343900,78.00,10.00,2026-03-25,沪金99\";\nvar hq_str_gds_AUTD=\"1013.68,0,1013.68,1013.70,1024.00,967.50,15:24:10,977.99,977.00,79972,6.00,5.00,2026-03-25,黄金延期\";\nvar hq_str_hf_XAU=\"4558.16,4474.260,4558.16,4558.51,4602.10,4455.98,15:24:00,4474.26,4475.66,0,0,0,2026-03-25,伦敦金（现货黄金）\";\nvar hq_str_hf_GC=\"4592.959,,4588.900,4589.100,4634.000,4491.700,15:24:18,4434.100,4506.100,0,2,1,2026-03-25,纽约黄金,0\";\nvar hq_str_USDCNY=\"15:23:30,6.8938,6.8948,6.8913,150,6.8913,6.8965,6.8815,6.8943,美元人民币,2026-03-25\";","note":"国内源: 代理人民币金价(基于最近有效样本比例，参考 03-25 15:23)；国际源: 新浪 hf_XAU 伦敦金现货"},{"id":4620,"fetched_at":"2026-03-25T15:23:35.136344+08:00","shfe_price_cny_per_g":1013.4864,"london_price_usd_per_oz":4556.79,"usdcny_rate":6.894,"london_price_cny_per_g":1010.0,"premium_cny_per_g":3.4864,"poll_interval_seconds":60,"both_markets_open":0,"shfe_market_open":0,"london_market_open":1,"alert_triggered":0,"raw_payload":"var hq_str_nf_AU0=\"黄金连续,150000,977.000,1027.880,970.260,1013.960,1013.860,1013.960,1013.960,998.740,979.240,1,51,169532.000,317182,沪,黄金,2026-03-25,1,,,,,,,,,998.742,0.000,0,0.000,0,0.000,0,0.000,0,0.000,0,0.000,0,0.000,0,0.000,0\";\nvar hq_str_gds_AU9999=\"1014.00,0,1014.01,1014.50,1028.99,965.10,15:23:09,979.56,980.00,1342600,200.00,152.00,2026-03-25,沪金99\";\nvar hq_str_gds_AUTD=\"1013.79,0,1013.30,1013.78,1024.00,967.50,15:23:09,977.99,977.00,79896,1.00,2.00,2026-03-25,黄金延期\";\nvar hq_str_hf_XAU=\"4556.79,4474.260,4556.79,4557.14,4602.10,4455.98,15:23:00,4474.26,4475.66,0,0,0,2026-03-25,伦敦金（现货黄金）\";\nvar hq_str_hf_GC=\"4593.060,,4588.500,4588.600,4634.000,4491.700,15:23:11,4434.100,4506.100,0,1,1,2026-03-25,纽约黄金,0\";\nvar hq_str_USDCNY=\"15:23:05,6.8940,6.8950,6.8913,150,6.8913,6.8965,6.8815,6.8945,美元人民币,2026-03-25\";","note":"国内源: 代理人民币金价(基于最近有效样本比例，参考 03-25 15:22)；国际源: 新浪 hf_XAU 伦敦金现货"},{"id":4619,"fetched_at":"2026-03-25T15:22:35.143255+08:00","shfe_price_cny_per_g":1013.7126,"london_price_usd_per_oz":4558.27,"usdcny_rate":6.8933,"london_price_cny_per_g":1010.2254,"premium_cny_per_g":3.4872,"poll_interval_seconds":60,"both_markets_open":0,"shfe_market_open":0,"london_market_open":1,"alert_triggered":0,"raw_payload":"var hq_str_nf_AU0=\"黄金连续,150000,977.000,1027.880,970.260,1013.960,1013.860,1013.960,1013.960,998.740,979.240,1,51,169532.000,317182,沪,黄金,2026-03-25,1,,,,,,,,,998.742,0.000,0,0.000,0,0.000,0,0.000,0,0.000,0,0.000,0,0.000,0,0.000,0\";\nvar hq_str_gds_AU9999=\"1014.50,0,1014.50,1015.60,1028.99,965.10,15:22:10,979.56,980.00,1341600,135.00,776.00,2026-03-25,沪金99\";\nvar hq_str_gds_AUTD=\"1013.79,0,1013.93,1014.08,1024.00,967.50,15:22:09,977.99,977.00,79818,1.00,1.00,2026-03-25,黄金延期\";\nvar hq_str_hf_XAU=\"4558.27,4474.260,4558.27,4558.62,4602.10,4455.98,15:22:00,4474.26,4475.66,0,0,0,2026-03-25,伦敦金（现货黄金）\";\nvar hq_str_hf_GC=\"4593.520,,4589.800,4590.200,4634.000,4491.700,15:22:28,4434.100,4506.100,0,5,1,2026-03-25,纽约黄金,0\";\nvar hq_str_USDCNY=\"15:21:27,6.8933,6.8943,6.8913,150,6.8913,6.8965,6.8815,6.8938,美元人民币,2026-03-25\";","note":"国内源: 代理人民币金价(基于最近有效样本比例，参考 03-25 15:21)；国际源: 新浪 hf_XAU 伦敦金现货"},{"id":4618,"fetched_at":"2026-03-25T15:21:35.124511+08:00","shfe_price_cny_per_g":1014.683,"london_price_usd_per_oz":4562.7,"usdcny_rate":6.8932,"london_price_cny_per_g":1011.1925,"premium_cny_per_g":3.4905,"poll_interval_seconds":60,"both_markets_open":0,"shfe_market_open":0,"london_market_open":1,"alert_triggered":0,"raw_payload":"var hq_str_nf_AU0=\"黄金连续,150000,977.000,1027.880,970.260,1013.960,1013.860,1013.960,1013.960,998.740,979.240,1,51,169532.000,317182,沪,黄金,2026-03-25,1,,,,,,,,,998.742,0.000,0,0.000,0,0.000,0,0.000,0,0.000,0,0.000,0,0.000,0,0.000,0\";\nvar hq_str_gds_AU9999=\"1014.50,0,1014.20,1014.50,1028.99,965.10,15:21:09,979.56,980.00,1340600,100.00,268.00,2026-03-25,沪金99\";\nvar hq_str_gds_AUTD=\"1014.70,0,1014.68,1014.80,1024.00,967.50,15:21:10,977.99,977.00,79770,1.00,1.00,2026-03-25,黄金延期\";\nvar hq_str_hf_XAU=\"4562.70,4474.260,4562.70,4563.05,4602.10,4455.98,15:21:00,4474.26,4475.66,0,0,0,2026-03-25,伦敦金（现货黄金）\";\nvar hq_str_hf_GC=\"4596.470,,4591.800,4592.300,4634.000,4491.700,15:21:27,4434.100,4506.100,0,1,1,2026-03-25,纽约黄金,0\";\nvar hq_str_USDCNY=\"15:20:25,6.8932,6.8942,6.8913,150,6.8913,6.8965,6.8815,6.8937,美元人民币,2026-03-25\";","note":"国内源: 代理人民币金价(基于最近有效样本比例，参考 03-25 15:20)；国际源: 新浪 hf_XAU 伦敦金现货"},{"id":4617,"fetched_at":"2026-03-25T15:20:35.122997+08:00","shfe_price_cny_per_g":1014.6582,"london_price_usd_per_oz":4562.39,"usdcny_rate":6.8935,"london_price_cny_per_g":1011.1678,"premium_cny_per_g":3.4904,"poll_interval_seconds":60,"both_markets_open":0,"shfe_market_open":0,"london_market_open":1,"alert_triggered":0,"raw_payload":"var hq_str_nf_AU0=\"黄金连续,150000,977.000,1027.880,970.260,1013.960,1013.860,1013.960,1013.960,998.740,979.240,1,51,169532.000,317182,沪,黄金,2026-03-25,1,,,,,,,,,998.742,0.000,0,0.000,0,0.000,0,0.000,0,0.000,0,0.000,0,0.000,0,0.000,0\";\nvar hq_str_gds_AU9999=\"1015.10,0,1014.50,1015.60,1028.99,965.10,15:20:06,979.56,980.00,1337700,120.00,727.00,2026-03-25,沪金99\";\nvar hq_str_gds_AUTD=\"1014.95,0,1014.80,1014.95,1024.00,967.50,15:20:07,977.99,977.00,79766,1.00,1.00,2026-03-25,黄金延期\";\nvar hq_str_hf_XAU=\"4562.39,4474.260,4562.39,4562.74,4602.10,4455.98,15:20:00,4474.26,4475.66,0,0,0,2026-03-25,伦敦金（现货黄金）\";\nvar hq_str_hf_GC=\"4597.460,,4593.300,4593.700,4634.000,4491.700,15:20:26,4434.100,4506.100,0,2,2,2026-03-25,纽约黄金,0\";\nvar hq_str_USDCNY=\"15:19:56,6.8935,6.8957,6.8913,150,6.8913,6.8965,6.8815,6.8946,美元人民币,2026-03-25\";","note":"国内源: 代理人民币金价(基于最近有效样本比例，参考 03-25 15:19)；国际源: 新浪 hf_XAU 伦敦金现货"},{"id":4616,"fetched_at":"2026-03-25T15:19:35.143794+08:00","shfe_price_cny_per_g":1014.4488,"london_price_usd_per_oz":4561.25,"usdcny_rate":6.8938,"london_price_cny_per_g":1010.9592,"premium_cny_per_g":3.4896,"poll_interval_seconds":60,"both_markets_open":0,"shfe_market_open":0,"london_market_open":1,"alert_triggered":0,"raw_payload":"var hq_str_nf_AU0=\"黄金连续,150000,977.000,1027.880,970.260,1013.960,1013.860,1013.960,1013.960,998.740,979.240,1,51,169532.000,317182,沪,黄金,2026-03-25,1,,,,,,,,,998.742,0.000,0,0.000,0,0.000,0,0.000,0,0.000,0,0.000,0,0.000,0,0.000,0\";\nvar hq_str_gds_AU9999=\"1015.10,0,1015.10,1016.00,1028.99,965.10,15:19:09,979.56,980.00,1335200,12.00,11.00,2026-03-25,沪金99\";\nvar hq_str_gds_AUTD=\"1014.88,0,1014.60,1014.75,1024.00,967.50,15:19:10,977.99,977.00,79718,1.00,1.00,2026-03-25,黄金延期\";\nvar hq_str_hf_XAU=\"4561.25,4474.260,4561.25,4561.60,4602.10,4455.98,15:19:00,4474.26,4475.66,0,0,0,2026-03-25,伦敦金（现货黄金）\";\nvar hq_str_hf_GC=\"4595.820,,4592.200,4592.500,4634.000,4491.700,15:19:20,4434.100,4506.100,0,1,1,2026-03-25,纽约黄金,0\";\nvar hq_str_USDCNY=\"15:18:22,6.8938,6.8948,6.8913,150,6.8913,6.8965,6.8815,6.8943,美元人民币,2026-03-25\";","note":"国内源: 代理人民币金价(基于最近有效样本比例，参考 03-25 15:18)；国际源: 新浪 hf_XAU 伦敦金现货"},{"id":4615,"fetched_at":"2026-03-25T15:18:35.140283+08:00","shfe_price_cny_per_g":1014.551,"london_price_usd_per_oz":4561.18,"usdcny_rate":6.8946,"london_price_cny_per_g":1011.061,"premium_cny_per_g":3.49,"poll_interval_seconds":60,"both_markets_open":0,"shfe_market_open":0,"london_market_open":1,"alert_triggered":0,"raw_payload":"var hq_str_nf_AU0=\"黄金连续,150000,977.000,1027.880,970.260,1013.960,1013.860,1013.960,1013.960,998.740,979.240,1,51,169532.000,317182,沪,黄金,2026-03-25,1,,,,,,,,,998.742,0.000,0,0.000,0,0.000,0,0.000,0,0.000,0,0.000,0,0.000,0,0.000,0\";\nvar hq_str_gds_AU9999=\"1015.50,0,1015.00,1015.50,1028.99,965.10,15:18:07,979.56,980.00,1334000,78.00,998.00,2026-03-25,沪金99\";\nvar hq_str_gds_AUTD=\"1014.45,0,1014.30,1014.45,1024.00,967.50,15:18:10,977.99,977.00,79666,2.00,8.00,2026-03-25,黄金延期\";\nvar hq_str_hf_XAU=\"4561.18,4474.260,4561.18,4561.53,4602.10,4455.98,15:18:00,4474.26,4475.66,0,0,0,2026-03-25,伦敦金（现货黄金）\";\nvar hq_str_hf_GC=\"4595.636,,4592.100,4592.400,4634.000,4491.700,15:18:14,4434.100,4506.100,0,2,4,2026-03-25,纽约黄金,0\";\nvar hq_str_USDCNY=\"15:18:03,6.8946,6.8948,6.8860,147,6.8887,6.8986,6.8839,6.8952,美元人民币,2026-03-25\";","note":"国内源: 代理人民币金价(基于最近有效样本比例，参考 03-25 15:17)；国际源: 新浪 hf_XAU 伦敦金现货"},{"id":4614,"fetched_at":"2026-03-25T15:17:35.132578+08:00","shfe_price_cny_per_g":1014.1664,"london_price_usd_per_oz":4559.98,"usdcny_rate":6.8938,"london_price_cny_per_g":1010.6777,"premium_cny_per_g":3.4887,"poll_interval_seconds":60,"both_markets_open":0,"shfe_market_open":0,"london_market_open":1,"alert_triggered":0,"raw_payload":"var hq_str_nf_AU0=\"黄金连续,150000,977.000,1027.880,970.260,1013.960,1013.860,1013.960,1013.960,998.740,979.240,1,51,169532.000,317182,沪,黄金,2026-03-25,1,,,,,,,,,998.742,0.000,0,0.000,0,0.000,0,0.000,0,0.000,0,0.000,0,0.000,0,0.000,0\";\nvar hq_str_gds_AU9999=\"1014.60,0,1014.00,1014.60,1028.99,965.10,15:17:09,979.56,980.00,1333000,30.00,80.00,2026-03-25,沪金99\";\nvar hq_str_gds_AUTD=\"1014.03,0,1014.14,1014.29,1024.00,967.50,15:17:10,977.99,977.00,79644,1.00,1.00,2026-03-25,黄金延期\";\nvar hq_str_hf_XAU=\"4559.98,4474.260,4559.98,4560.33,4602.10,4455.98,15:17:00,4474.26,4475.66,0,0,0,2026-03-25,伦敦金（现货黄金）\";\nvar hq_str_hf_GC=\"4595.325,,4591.200,4591.600,4634.000,4491.700,15:17:25,4434.100,4506.100,0,1,1,2026-03-25,纽约黄金,0\";\nvar hq_str_USDCNY=\"15:16:51,6.8938,6.8956,6.8913,150,6.8913,6.8965,6.8815,6.8947,美元人民币,2026-03-25\";","note":"国内源: 代理人民币金价(基于最近有效样本比例，参考 03-25 15:16)；国际源: 新浪 hf_XAU 伦敦金现货"},{"id":4613,"fetched_at":"2026-03-25T15:16:35.139619+08:00","shfe_price_cny_per_g":1013.7069,"london_price_usd_per_oz":4557.98,"usdcny_rate":6.8937,"london_price_cny_per_g":1010.2198,"premium_cny_per_g":3.4871,"poll_interval_seconds":60,"both_markets_open":0,"shfe_market_open":0,"london_market_open":1,"alert_triggered":0,"raw_payload":"var hq_str_nf_AU0=\"黄金连续,150000,977.000,1027.880,970.260,1013.960,1013.860,1013.960,1013.960,998.740,979.240,1,51,169532.000,317182,沪,黄金,2026-03-25,1,,,,,,,,,998.742,0.000,0,0.000,0,0.000,0,0.000,0,0.000,0,0.000,0,0.000,0,0.000,0\";\nvar hq_str_gds_AU9999=\"1014.00,0,1013.50,1014.60,1028.99,965.10,15:16:07,979.56,980.00,1332800,4.00,105.00,2026-03-25,沪金99\";\nvar hq_str_gds_AUTD=\"1014.00,0,1013.80,1014.40,1024.00,967.50,15:16:08,977.99,977.00,79512,1.00,5.00,2026-03-25,黄金延期\";\nvar hq_str_hf_XAU=\"4557.98,4474.260,4557.98,4558.33,4602.10,4455.98,15:16:00,4474.26,4475.66,0,0,0,2026-03-25,伦敦金（现货黄金）\";\nvar hq_str_hf_GC=\"4592.876,,4588.800,4589.200,4634.000,4491.700,15:16:24,4434.100,4506.100,0,4,2,2026-03-25,纽约黄金,0\";\nvar hq_str_USDCNY=\"15:15:48,6.8937,6.8947,6.8913,150,6.8913,6.8965,6.8815,6.8942,美元人民币,2026-03-25\";","note":"国内源: 代理人民币金价(基于最近有效样本比例，参考 03-25 15:15)；国际源: 新浪 hf_XAU 伦敦金现货"},{"id":4612,"fetched_at":"2026-03-25T15:15:35.134906+08:00","shfe_price_cny_per_g":1013.5908,"london_price_usd_per_oz":4557.26,"usdcny_rate":6.894,"london_price_cny_per_g":1010.1041,"premium_cny_per_g":3.4867,"poll_interval_seconds":60,"both_markets_open":0,"shfe_market_open":0,"london_market_open":1,"alert_triggered":0,"raw_payload":"var hq_str_nf_AU0=\"黄金连续,150000,977.000,1027.880,970.260,1013.960,1013.860,1013.960,1013.960,998.740,979.240,1,51,169532.000,317182,沪,黄金,2026-03-25,1,,,,,,,,,998.742,0.000,0,0.000,0,0.000,0,0.000,0,0.000,0,0.000,0,0.000,0,0.000,0\";\nvar hq_str_gds_AU9999=\"1014.00,0,1013.00,1013.50,1028.99,965.10,15:15:07,979.56,980.00,1331100,284.00,277.00,2026-03-25,沪金99\";\nvar hq_str_gds_AUTD=\"1013.77,0,1013.77,1014.48,1024.00,967.50,15:15:05,977.99,977.00,79474,16.00,1.00,2026-03-25,黄金延期\";\nvar hq_str_hf_XAU=\"4557.26,4474.260,4557.26,4557.61,4602.10,4455.98,15:15:00,4474.26,4475.66,0,0,0,2026-03-25,伦敦金（现货黄金）\";\nvar hq_str_hf_GC=\"4591.680,,4587.600,4588.000,4634.000,4491.700,15:15:13,4434.100,4506.100,0,1,1,2026-03-25,纽约黄金,0\";\nvar hq_str_USDCNY=\"15:15:03,6.8940,6.8950,6.8913,150,6.8913,6.8965,6.8815,6.8945,美元人民币,2026-03-25\";","note":"国内源: 代理人民币金价(基于最近有效样本比例，参考 03-25 15:14)；国际源: 新浪 hf_XAU 伦敦金现货"}],"gold_reversal":{"latest_sample":{"id":3640,"fetched_at":"2026-03-25T15:34:35.775837+08:00","gold_price_usd_per_oz":4554.97,"usdcny_rate":6.8953,"price_signal":0,"political_signal":1,"war_signal":0,"signal_level":4,"triggered_conditions":"political","note":"盘面: 现价 4554.97 / 低点 4544.77 / MA15 4558.68 / 反弹 0.22%；国内源: 代理人民币金价(基于最近有效样本比例，参考 03-25 15:34)；国际源: 新浪 hf_XAU 伦敦金现货；10Y: 现值 4.340% / 高点 4.390% / 24.0h回落 5.00bp (阈值 1.00bp)；政治事件: 兵临华容道：从一份流传的15点美伊停战协议，看透中东地缘底牌 | 原油下跌，特朗普推迟打击5天，是和谈还是心理战？；RSS独立调度: 上次抓取成功(2026-03-25 14:43:19)","us10y_signal":0},"recent_alerts":[{"id":16,"sample_id":2613,"sent_at":"2026-03-24T22:28:36.280036+08:00","signal_level":2,"triggered_conditions":"price,political,war","success":1,"response_text":"默认机器人:ok:{\"errcode\":0,\"errmsg\":\"ok\"}","webhook_url":"https://oapi.dingtalk.com/robot/send?access_token=ea508357bbcd5c6801fa5cb91bf0dc9126c4f2c04f5a64bbd2fdae690f0bc56f"},{"id":15,"sample_id":1435,"sent_at":"2026-03-24T02:49:36.217936+08:00","signal_level":2,"triggered_conditions":"price,political,war","success":1,"response_text":"默认机器人:ok:{\"errcode\":0,\"errmsg\":\"ok\"}","webhook_url":"https://oapi.dingtalk.com/robot/send?access_token=ea508357bbcd5c6801fa5cb91bf0dc9126c4f2c04f5a64bbd2fdae690f0bc56f"},{"id":14,"sample_id":1384,"sent_at":"2026-03-24T01:58:36.063831+08:00","signal_level":2,"triggered_conditions":"price,political,war","success":1,"response_text":"默认机器人:ok:{\"errcode\":0,\"errmsg\":\"ok\"}","webhook_url":"https://oapi.dingtalk.com/robot/send?access_token=ea508357bbcd5c6801fa5cb91bf0dc9126c4f2c04f5a64bbd2fdae690f0bc56f"},{"id":13,"sample_id":1353,"sent_at":"2026-03-24T01:27:36.029022+08:00","signal_level":2,"triggered_conditions":"price,political,war","success":1,"response_text":"默认机器人:ok:{\"errcode\":0,\"errmsg\":\"ok\"}","webhook_url":"https://oapi.dingtalk.com/robot/send?access_token=ea508357bbcd5c6801fa5cb91bf0dc9126c4f2c04f5a64bbd2fdae690f0bc56f"},{"id":12,"sample_id":1076,"sent_at":"2026-03-23T20:50:35.957030+08:00","signal_level":2,"triggered_conditions":"price,political,war","success":1,"response_text":"默认机器人:ok:{\"errcode\":0,\"errmsg\":\"ok\"}","webhook_url":"https://oapi.dingtalk.com/robot/send?access_token=ea508357bbcd5c6801fa5cb91bf0dc9126c4f2c04f5a64bbd2fdae690f0bc56f"},{"id":11,"sample_id":1045,"sent_at":"2026-03-23T20:19:36.125692+08:00","signal_level":2,"triggered_conditions":"price,political,war","success":1,"response_text":"默认机器人:ok:{\"errcode\":0,\"errmsg\":\"ok\"}","webhook_url":"https://oapi.dingtalk.com/robot/send?access_token=ea508357bbcd5c6801fa5cb91bf0dc9126c4f2c04f5a64bbd2fdae690f0bc56f"},{"id":10,"sample_id":999,"sent_at":"2026-03-23T19:33:35.953551+08:00","signal_level":2,"triggered_conditions":"price,political,war","success":1,"response_text":"默认机器人:ok:{\"errcode\":0,\"errmsg\":\"ok\"}","webhook_url":"https://oapi.dingtalk.com/robot/send?access_token=ea508357bbcd5c6801fa5cb91bf0dc9126c4f2c04f5a64bbd2fdae690f0bc56f"},{"id":9,"sample_id":968,"sent_at":"2026-03-23T19:02:35.863128+08:00","signal_level":2,"triggered_conditions":"price,political,war","success":1,"response_text":"默认机器人:ok:{\"errcode\":0,\"errmsg\":\"ok\"}","webhook_url":"https://oapi.dingtalk.com/robot/send?access_token=ea508357bbcd5c6801fa5cb91bf0dc9126c4f2c04f5a64bbd2fdae690f0bc56f"},{"id":8,"sample_id":860,"sent_at":"2026-03-23T17:15:36.072045+08:00","signal_level":2,"triggered_conditions":"price,political,war","success":1,"response_text":"默认机器人:ok:{\"errcode\":0,\"errmsg\":\"ok\"}","webhook_url":"https://oapi.dingtalk.com/robot/send?access_token=ea508357bbcd5c6801fa5cb91bf0dc9126c4f2c04f5a64bbd2fdae690f0bc56f"},{"id":7,"sample_id":826,"sent_at":"2026-03-23T16:41:36.053117+08:00","signal_level":2,"triggered_conditions":"price,political,war","success":1,"response_text":"默认机器人:ok:{\"errcode\":0,\"errmsg\":\"ok\"}","webhook_url":"https://oapi.dingtalk.com/robot/send?access_token=ea508357bbcd5c6801fa5cb91bf0dc9126c4f2c04f5a64bbd2fdae690f0bc56f"}],"recent_runs":[{"id":3640,"fetched_at":"2026-03-25T15:34:35.775837+08:00","success":1,"poll_interval_seconds":60,"duration_ms":650,"rss_error_count":0,"error_message":null},{"id":3639,"fetched_at":"2026-03-25T15:33:35.764314+08:00","success":1,"poll_interval_seconds":60,"duration_ms":828,"rss_error_count":0,"error_message":null},{"id":3638,"fetched_at":"2026-03-25T15:32:35.779953+08:00","success":1,"poll_interval_seconds":60,"duration_ms":647,"rss_error_count":0,"error_message":null},{"id":3637,"fetched_at":"2026-03-25T15:31:35.907413+08:00","success":1,"poll_interval_seconds":60,"duration_ms":667,"rss_error_count":0,"error_message":null},{"id":3636,"fetched_at":"2026-03-25T15:30:35.921229+08:00","success":1,"poll_interval_seconds":60,"duration_ms":523,"rss_error_count":0,"error_message":null},{"id":3635,"fetched_at":"2026-03-25T15:29:35.933157+08:00","success":1,"poll_interval_seconds":60,"duration_ms":501,"rss_error_count":0,"error_message":null},{"id":3634,"fetched_at":"2026-03-25T15:28:35.907395+08:00","success":1,"poll_interval_seconds":60,"duration_ms":516,"rss_error_count":0,"error_message":null},{"id":3633,"fetched_at":"2026-03-25T15:27:35.745440+08:00","success":1,"poll_interval_seconds":60,"duration_ms":797,"rss_error_count":0,"error_message":null},{"id":3632,"fetched_at":"2026-03-25T15:26:35.906427+08:00","success":1,"poll_interval_seconds":60,"duration_ms":500,"rss_error_count":0,"error_message":null},{"id":3631,"fetched_at":"2026-03-25T15:25:36.166240+08:00","success":1,"poll_interval_seconds":60,"duration_ms":488,"rss_error_count":0,"error_message":null}],"recent_events":[{"id":579,"fetched_at":"2026-03-25T14:13:18.358707+08:00","published_at":"2026-03-25T05:28:01+00:00","source":"虎嗅","feed_url":"https://rss.huxiu.com/","title":"兵临华容道：从一份流传的15点美伊停战协议，看透中东地缘底牌","link":"https://www.huxiu.com/article/4845180.html?f=rss","summary":"本文来自微信公众号： 行业报告研究院 ，作者：玖峰 最近几天，关于美国与伊朗正在通过巴基斯坦等渠道接触，并抛出了一份包含15项核心条款的停火协议的消息，在各大媒体和政经圈子里引发了高度关注。 不同于很多自媒体渲染的“和平曙光”，当你安静下来，仔细对照着流传出来的这15条核心条款逐一推敲时，你会得出一个极其残酷的结论：这根本不是一份基于对等基础的停战协约，而是一份要求对手在物理和地政层面彻底“解除武装”的条书。 执行分类 核心要点 具体涵盖细节条款 核武清零(美方要求) 1.彻底解除核能力2.永久性弃核承诺3.境内禁铀浓缩 拆除现有核能力战略储备；签署不可逆的不寻求核武器协议；禁止在本土进行核燃料离心与研发 核武清零(美方要求) 4.大规模移交存货5.点名设施拆毁6.无死角全面核查 交由IAEA带走60%丰度、共","event_type":"political","matched_keywords":"停火","content_hash":"aee6d8cf690c28f52f48920f4743a09155ff73ab79a639dec8bcabcc4196b7a0:political","impact_score":8,"impact_level":"高","impact_note":"利好词命中2个；地缘缓和信号，升分"},{"id":573,"fetched_at":"2026-03-25T13:13:18.158850+08:00","published_at":"2026-03-25T05:00:00+00:00","source":"虎嗅","feed_url":"https://rss.huxiu.com/","title":"原油下跌，特朗普推迟打击5天，是和谈还是心理战？","link":"https://www.huxiu.com/article/4844679.html?f=rss","summary":"别让这场不该开始的战争继续下去了","event_type":"political","matched_keywords":"和谈","content_hash":"1f180f26704a8a55c2f8f0645d8986b5dac91a7adf649b29dbe602c2c827c3e1:political","impact_score":6,"impact_level":"中","impact_note":"利好词命中1个"},{"id":571,"fetched_at":"2026-03-25T12:13:20.299118+08:00","published_at":"2026-03-25T03:54:36+00:00","source":"金十数据","feed_url":"http://rss.jintiankansha.me/rss/GM3DSNZUGJ6DOYTEG5RWENZRGUZDENLDGAYGMMDGMRSTONBRMUYWMM3FMQ2DGYZXMZSTGNDGG4YQ====","title":"一边是停火方案和五天暂停带来的短暂缓和，一边是市场对谈判真假始终半信半疑，国际现货黄金从连跌深坑里抬头后，这段修复能走多远？","link":"https://xnews.jin10.com/details/214447","summary":"一边是停火方案和五天暂停带来的短暂缓和，一边是市场对谈判真假始终半信半疑，国际现货黄金从连跌深坑里抬头后，这段修复能走多远？","event_type":"political","matched_keywords":"停火,谈判","content_hash":"5a987ed9e39e691a9ca58bd9f771ab9df4f198deb02a44eb3fac9644a99044f9:political","impact_score":7,"impact_level":"中","impact_note":"利好词命中1个；地缘缓和信号，升分"},{"id":559,"fetched_at":"2026-03-25T11:13:19.721320+08:00","published_at":"2026-03-25T03:08:20+00:00","source":"金十数据","feed_url":"http://rss.jintiankansha.me/rss/GM3DSNZUGJ6DOYTEG5RWENZRGUZDENLDGAYGMMDGMRSTONBRMUYWMM3FMQ2DGYZXMZSTGNDGG4YQ====","title":"霍尔木兹海峡连续多日无油轮通行，美伊却在“停火传闻”中反复拉锯。当海上储油逼近极限，伊朗强硬派的石油武器才刚亮出锋芒——油价的真正考验，或许远未到来.....","link":"https://xnews.jin10.com/details/214441","summary":"霍尔木兹海峡连续多日无油轮通行，美伊却在“停火传闻”中反复拉锯。当海上储油逼近极限，伊朗强硬派的石油武器才刚亮出锋芒——油价的真正考验，或许远未到来......","event_type":"political","matched_keywords":"停火","content_hash":"c059d2aadc630448902bd011e21075e7ed70e1257da1a54304610c6efe462d50:political","impact_score":6,"impact_level":"中","impact_note":"利好词命中1个；低可信表态词命中2个；地缘缓和信号，升分"},{"id":561,"fetched_at":"2026-03-25T11:43:20.232479+08:00","published_at":"2026-03-25T02:57:07+00:00","source":"Bloomberg Economics","feed_url":"https://quanwenrss.com/bloomberg/economics","title":"Indonesia Rupiah Rises Most in Six Months, Stocks Gain in Reopen","link":"https://www.bloomberg.com/news/articles/2026-03-25/indonesia-rupiah-rises-most-in-six-months-stocks-gain-in-reopen","summary":"Bloomberg News Image The Indonesian rupiah and stocks gained as domestic markets reopened after a week-long holiday, buoyed by hopes over the Trump administration’s push to ease Iran war tensions. 发布时间: 2026-03-25T10:57:07+08:00 作者: Prima Wirayani The Indonesian rupiah and stocks gained as domestic markets reopened after a week-long holiday, buoyed by hopes","event_type":"war","matched_keywords":"reopen","content_hash":"724d8c15df9b009078789fdcc86550f650d5764b467741d5c6520aa4061cb120:war","impact_score":7,"impact_level":"中","impact_note":"利好词命中1个；地缘缓和信号，升分"},{"id":562,"fetched_at":"2026-03-25T11:43:20.232479+08:00","published_at":"2026-03-25T02:53:55+00:00","source":"Bloomberg Economics","feed_url":"https://quanwenrss.com/bloomberg/economics","title":"US Drafts 15-Point Plan to End Iran War as Trump Pushes Talks","link":"https://www.bloomberg.com/news/articles/2026-03-25/us-drafts-15-point-plan-to-end-iran-war-as-trump-pushes-talks","summary":"Bloomberg News Image The US has drafted a 15-point plan intended to help bring the war with Iran to a close, according to people familiar with the matter, highlighting the intensifying urgency within the Trump administration to resolve the conflict as the economic toll mounts. 发布时间: 2026-03-25T10:53:55+08:00 作者: Josh Wingrove, Eric Martin and Jennifer A. Dlo","event_type":"political","matched_keywords":"talks","content_hash":"43148f5a75b54df368f2f15ea6f062ed7ce9367f13983fb7a5d34ea72dd7d9df:political","impact_score":6,"impact_level":"中","impact_note":"利好词命中1个"},{"id":575,"fetched_at":"2026-03-25T13:13:18.158850+08:00","published_at":"2026-03-25T02:53:55+00:00","source":"Bloomberg Economics","feed_url":"https://quanwenrss.com/bloomberg/economics","title":"US Forms 15-Point Plan to End Iran War as Trump Pushes Talks","link":"https://www.bloomberg.com/news/articles/2026-03-25/us-drafts-15-point-plan-to-end-iran-war-as-trump-pushes-talks","summary":"Bloomberg News Image The US has drafted a 15-point plan intended to help bring the war with Iran to a close, according to people familiar with the matter, highlighting the intensifying urgency within the Trump administration to resolve the conflict as the economic toll mounts. 发布时间: 2026-03-25T10:53:55+08:00 作者: Josh Wingrove, Eric Martin and Jennifer A. Dlo","event_type":"political","matched_keywords":"talks","content_hash":"3066877909bf7af1603cd4b4f0ca6af44ff9b42670f4e0df3ff298225d7f239d:political","impact_score":6,"impact_level":"中","impact_note":"利好词命中1个"},{"id":563,"fetched_at":"2026-03-25T11:43:20.232479+08:00","published_at":"2026-03-25T02:40:34+00:00","source":"Bloomberg Economics","feed_url":"https://quanwenrss.com/bloomberg/economics","title":"What Are the Possible Outcomes of the Iran War?","link":"https://www.bloomberg.com/news/videos/2026-03-25/what-are-the-possible-outcomes-of-the-iran-war-video","summary":"Bloomberg News Image Behnam Ben Taleblu of the Foundation for Defense of Democracies Iran Program analyzes potential endgames for the conflict between the US, Israel and Iran. He joins Bloomberg TV as the US says it is moving forward with negotiations with the Iranian regime. (Source: Bloomberg) 发布时间: 2026-03-25T10:40:34+08:00 作者: Bloomberg News","event_type":"political","matched_keywords":"negotiation","content_hash":"3c2c2ed47a58d75cabb214151fa078b6ae5bdf31459aa72ca2a9f08c150fc246:political","impact_score":5,"impact_level":"中","impact_note":"利好词命中1个；低可信表态词命中1个"},{"id":553,"fetched_at":"2026-03-25T10:43:18.188204+08:00","published_at":"2026-03-25T02:07:34+00:00","source":"金十数据","feed_url":"http://rss.jintiankansha.me/rss/GM3DSNZUGJ6DOYTEG5RWENZRGUZDENLDGAYGMMDGMRSTONBRMUYWMM3FMQ2DGYZXMZSTGNDGG4YQ====","title":"霍尔木兹海峡关闭，能避开海峡的阿联酋石油已飙至160美元。交易商警告：除非和谈迅速取得成果，否则中东特定品级原油的创纪录价格，将很快蔓延至美国乃至全球。...","link":"https://xnews.jin10.com/details/214432","summary":"霍尔木兹海峡关闭，能避开海峡的阿联酋石油已飙至160美元。交易商警告：除非和谈迅速取得成果，否则中东特定品级原油的创纪录价格，将很快蔓延至美国乃至全球。点击查看","event_type":"political","matched_keywords":"和谈","content_hash":"fa02fa1caedda283030397391d19f12aa68bab7258b5dc8a744200cbf7df3a9b:political","impact_score":6,"impact_level":"中","impact_note":"利好词命中1个"},{"id":554,"fetched_at":"2026-03-25T10:43:18.188204+08:00","published_at":"2026-03-25T02:00:38+00:00","source":"金十数据","feed_url":"http://rss.jintiankansha.me/rss/GM3DSNZUGJ6DOYTEG5RWENZRGUZDENLDGAYGMMDGMRSTONBRMUYWMM3FMQ2DGYZXMZSTGNDGG4YQ====","title":"日本首相高市早苗：（关于伊朗停火后的扫雷）将“视当时情况依法判断”，支持美国发挥建设性作用。","link":"","summary":"日本首相高市早苗：（关于伊朗停火后的扫雷）将“视当时情况依法判断”，支持美国发挥建设性作用。","event_type":"political","matched_keywords":"停火","content_hash":"afb8c05bc834bbced0aa8d3b42e1bee5f3fc3f514626f0b25587c2acb5b1fa36:political","impact_score":7,"impact_level":"中","impact_note":"利好词命中1个；地缘缓和信号，升分"},{"id":548,"fetched_at":"2026-03-25T09:43:18.591841+08:00","published_at":"2026-03-25T00:57:00+00:00","source":"Bloomberg Economics","feed_url":"https://quanwenrss.com/bloomberg/economics","title":"Trump Says Iran 'Wants to Make a Deal' As Costs Rise","link":"https://www.bloomberg.com/news/videos/2026-03-25/trump-says-iran-wants-to-make-a-deal-as-costs-rise-video","summary":"Bloomberg News Image President Donald Trump signaled that Iran had offered a “present” as a show of good faith in negotiations he has claimed are ongoing to end a 25-day conflict that’s upended global markets, even while he deploys more troops to the Middle East. Bloomberg's Laura Davison has the latest. (Source: Bloomberg) 发布时间: 2026-03-25T08:57:00+08:00 作者","event_type":"political","matched_keywords":"negotiation","content_hash":"b23858c39104cbf331e681a51d9d596af97dd930d1fbe3817cc4f72d3eeaebce:political","impact_score":5,"impact_level":"中","impact_note":"利好词命中1个；低可信表态词命中1个"},{"id":549,"fetched_at":"2026-03-25T09:43:18.591841+08:00","published_at":"2026-03-25T00:39:01+00:00","source":"Bloomberg Economics","feed_url":"https://quanwenrss.com/bloomberg/economics","title":"Indonesia Markets Reopen as Shifting Iran Headlines Spur Caution","link":"https://www.bloomberg.com/news/articles/2026-03-25/indonesia-markets-reopen-as-shifting-iran-headlines-spur-caution","summary":"Bloomberg News Image Indonesia’s markets are likely to grapple with fluctuating sentiment when they reopen Wednesday after a week-long holiday, as investors weigh rapidly shifting headlines on the Iran war and persistent concerns over fiscal and governance risks. 发布时间: 2026-03-25T08:39:01+08:00 作者: Matthew Burgess and Eduard Gismatullin Indonesia’s markets a","event_type":"war","matched_keywords":"reopen","content_hash":"63621369c86a3ecf6c683531af1a067ba9991ee4c759c3dc4c316eeced3da41b:war","impact_score":7,"impact_level":"中","impact_note":"利好词命中1个；地缘缓和信号，升分"},{"id":544,"fetched_at":"2026-03-25T08:13:19.065204+08:00","published_at":"2026-03-24T23:17:26+00:00","source":"金十数据","feed_url":"http://rss.jintiankansha.me/rss/GM3DSNZUGJ6DOYTEG5RWENZRGUZDENLDGAYGMMDGMRSTONBRMUYWMM3FMQ2DGYZXMZSTGNDGG4YQ====","title":"<b>据半岛电视台：以色列驻联合国代表称，以色列未参与美伊之间的谈判。</b>","link":"","summary":"据半岛电视台：以色列驻联合国代表称，以色列未参与美伊之间的谈判。","event_type":"political","matched_keywords":"谈判","content_hash":"d7f9889144f0c24a2cae32faf748b7f2fa2476874271bd8abc62f162215ddc49:political","impact_score":5,"impact_level":"中","impact_note":"未命中明显风险词，按基础分"},{"id":531,"fetched_at":"2026-03-25T07:43:18.404950+08:00","published_at":"2026-03-24T22:36:18+00:00","source":"Bloomberg Economics","feed_url":"https://quanwenrss.com/bloomberg/economics","title":"Oil Falls, US Stock Futures Climb on Iran Hopes: Markets Wrap","link":"https://www.bloomberg.com/news/articles/2026-03-24/stock-market-today-dow-s-p-live-updates","summary":"Bloomberg News Image Oil fell and US equity futures climbed as optimism grew over Washington’s efforts to end the nearly month-long Middle East conflict. 发布时间: 2026-03-25T06:36:18+08:00 作者: Rob Verdonck Oil fell and US equity futures climbed as optimism grew over Washington’s efforts to end the nearly month-long Middle East conflict. West Texas Intermediate","event_type":"political","matched_keywords":"ceasefire","content_hash":"badce5e00a221f492b8fc6dc19659e719e741264d4d9ccf85d6403cf3c89ed1a:political","impact_score":5,"impact_level":"中","impact_note":"未命中明显风险词，按基础分"},{"id":532,"fetched_at":"2026-03-25T07:43:18.404950+08:00","published_at":"2026-03-24T22:35:08+00:00","source":"Bloomberg Economics","feed_url":"https://quanwenrss.com/bloomberg/economics","title":"Gold Holds Gain After Reports of US Negotiations to End Iran War","link":"https://www.bloomberg.com/news/articles/2026-03-24/gold-holds-gain-after-reports-of-us-negotiations-to-end-iran-war","summary":"Bloomberg News Image Gold steadied after snapping a nine-day decline, as investors weighed reports that the US is seeking a diplomatic route to ending the war with Iran even as it sends more troops to the Middle East. 发布时间: 2026-03-25T06:35:08+08:00 作者: Yihui Xie Gold steadied after snapping a nine-day decline, as investors weighed reports that the US is see","event_type":"political","matched_keywords":"negotiation","content_hash":"61f27f69335e1b38dd96d4c011b5a5ea0871b23703d66253b869dd605921efd5:political","impact_score":6,"impact_level":"中","impact_note":"利好词命中1个"},{"id":547,"fetched_at":"2026-03-25T09:13:18.172512+08:00","published_at":"2026-03-24T22:35:08+00:00","source":"Bloomberg Economics","feed_url":"https://quanwenrss.com/bloomberg/economics","title":"Gold Extends Gains as Reports of Iran War Talks Offer Respite","link":"https://www.bloomberg.com/news/articles/2026-03-24/gold-holds-gain-after-reports-of-us-negotiations-to-end-iran-war","summary":"Bloomberg News Image Gold extended gains after reports that the US is seeking a diplomatic route to ending the war in the Middle East snapped the precious metal’s nine-day losing streak. 发布时间: 2026-03-25T06:35:08+08:00 作者: Yihui Xie Gold extended gains after reports that the US is seeking a diplomatic route to ending the war in the Middle East snapped the pr","event_type":"political","matched_keywords":"talks","content_hash":"66e3ff58634cf0759f2b14a8ea9fad365500704ad0c1dc4a3c6749e7bf47eec0:political","impact_score":6,"impact_level":"中","impact_note":"利好词命中1个"},{"id":524,"fetched_at":"2026-03-25T06:43:19.085211+08:00","published_at":"2026-03-24T22:30:04+00:00","source":"金十数据","feed_url":"http://rss.jintiankansha.me/rss/GM3DSNZUGJ6DOYTEG5RWENZRGUZDENLDGAYGMMDGMRSTONBRMUYWMM3FMQ2DGYZXMZSTGNDGG4YQ====","title":"<b>国内新闻</b><br/><span class=\"section-news\">1. 王毅同伊朗外长阿拉格齐通电话。</span><br/><span class=\"section-news\">2. 高盛维持对中国股票（A股和港...","link":"","summary":"国内新闻 1. 王毅同伊朗外长阿拉格齐通电话。 2. 高盛维持对中国股票（A股和港股）的高配建议。 3. 央行：3月25日将开展5000亿元MLF操作，期限为1年期。 4. 市场监管总局召开2026年价格监督检查和反不正当竞争工作座谈会。 5. 周大福推迟“一口价”产品调价，门店称：已拿到新价签，只等总部通知。 国际新闻 1. 菲律宾宣布国家能源紧急状态。 2. 民调：特朗普支持率降至重返白宫以来最低。 3. 美媒：美司法部承认对鲍威尔的调查缺乏证据。 4. 欧盟推迟原定4月15日提交的永久禁止进口俄油提案。 5. 世界黄金协会：受地缘政治风险推动，更多央行将增持黄金。 6. 印度将与阿联酋的黄金进口关税配额授权有效期延长至6月30日。 7. 知情人士：土耳其正考虑动用其价值1350亿美元的黄金储备，以支撑不断","event_type":"political","matched_keywords":"停火,谈判,和谈","content_hash":"e89485ab111eba06073f688118c36a238e993ee8e11f6bb66488a79786e6af46:political","impact_score":5,"impact_level":"中","impact_note":"未命中明显风险词，按基础分"},{"id":525,"fetched_at":"2026-03-25T06:43:19.085211+08:00","published_at":"2026-03-24T22:22:02+00:00","source":"金十数据","feed_url":"http://rss.jintiankansha.me/rss/GM3DSNZUGJ6DOYTEG5RWENZRGUZDENLDGAYGMMDGMRSTONBRMUYWMM3FMQ2DGYZXMZSTGNDGG4YQ====","title":"英媒：伊朗偏好与万斯谈判，指责库什纳与威特科夫“背信弃义”","link":"","summary":"金十数据3月25日讯，据英国每日电讯报报道，伊朗拒绝与美国中东问题特使威特科夫和特朗普的女婿库什纳进行谈判，指责他们“背信弃义”。海湾消息人士表示，伊朗方面不会与威特科夫以及库什纳坐下来谈，因为在他们二月份举行会谈几小时后，德黑兰就遭到了军事打击。美国副总统万斯在这场冲突中基本保持沉默，若本周晚些时候在巴基斯坦伊斯兰堡重启谈判，万斯被视为首席谈判代表的人选。“万斯是更倾向的人选，”一位海湾消息人士谈及伊朗的态度时表示。“他们不想和库什纳和威特科夫合作，因为他们背信弃义。”消息人士称，伊朗认为万斯会信守承诺，他的参与被视为是与伊朗议会议长卡利巴夫进行谈判的合适层级。这位副总统可能作为美国谈判团队新的负责人，这表明白宫有意避免进一步的经济损失并缓和局势，尽管结束战争的战略仍不明朗。","event_type":"political","matched_keywords":"谈判,会谈","content_hash":"f6f33a6d50147f4e5cbb17da5b5feb361a3d4544a07027bb5428e7046e9254fa:political","impact_score":4,"impact_level":"低","impact_note":"利好词命中1个；利空词命中1个；低可信表态词命中1个"},{"id":526,"fetched_at":"2026-03-25T06:43:19.085211+08:00","published_at":"2026-03-24T22:07:14+00:00","source":"金十数据","feed_url":"http://rss.jintiankansha.me/rss/GM3DSNZUGJ6DOYTEG5RWENZRGUZDENLDGAYGMMDGMRSTONBRMUYWMM3FMQ2DGYZXMZSTGNDGG4YQ====","title":"<b>美以伊冲突：</b><br/><b>①伊朗</b><br/><span class=\"section-news\">1. 伊朗与巴基斯坦高层连续通话。</span><br/><span class=\"section-news\">2. 伊朗称摧...","link":"","summary":"美以伊冲突： ①伊朗 1. 伊朗与巴基斯坦高层连续通话。 2. 伊朗称摧毁两枚AGM-158巡航导弹。 3. 伊朗警方逮捕与敌方有关联者466人。 4. 伊朗国家安全委员会：伊朗并未提出任何停火建议。 5. 当地官员称，伊朗霍拉姆沙赫尔电厂在袭击后未出现任何干扰。 6. 美媒：伊朗消息人士表示美伊双方确有接触，但尚未达到全面谈判的程度。 7. 伊朗任命穆罕默德·巴盖尔·佐尔加德尔为伊朗最高国家安全委员会秘书。 8. 美媒：伊朗最高军事指挥部发言人表示，武装部队将“战斗到完全胜利。” 9. 伊朗再次被曝索要单次200万美元“过路费”，伊朗官方此前曾否认了这一说法。 10. 一名巴基斯坦官员表示，伊朗在与美国的谈判中存在巨大的不信任，并不确定能达成协议。 11. 伊朗革命卫队警告以军，若以色列袭击巴勒斯坦领土和黎巴","event_type":"political","matched_keywords":"停火,谈判,斡旋,和谈","content_hash":"3b93247a342d4befa3341af8d076338e018c01afa34ee977f4d4325d6772916b:political","impact_score":4,"impact_level":"低","impact_note":"利好词命中2个；利空词命中3个；地缘紧张升级，降分；地缘缓和信号，升分"},{"id":523,"fetched_at":"2026-03-25T06:43:19.085211+08:00","published_at":"2026-03-24T21:44:50+00:00","source":"Bloomberg Economics","feed_url":"https://quanwenrss.com/bloomberg/economics","title":"EU Agrees to Trade Deal, War Hits Wheat Farmers","link":"https://www.bloomberg.com/news/newsletters/2026-03-24/eu-agrees-free-trade-deal-wheat-farmers-australia-briefing","summary":"Bloomberg News Image Get caught up. 发布时间: 2026-03-25T05:44:50+08:00 作者: Sharon Klyne What’s happening now and Australia agreed to a free-trade deal , wrapping up almost a decade of talks as the two sides push to tighten ties and reinvigorate a rules-based order that’s under assault from the Trump administration. Ursula von der Leyen, left, and Anthony Albane","event_type":"political","matched_keywords":"talks","content_hash":"be1826b6bc2284efd828efde7b0b44df81c31f7f7e2a664dc48bab838b8b1f30:political","impact_score":6,"impact_level":"中","impact_note":"利好词命中1个"}],"recent_rss_fetch_runs":[{"id":114,"fetched_at":"2026-03-25T14:43:19.160524+08:00","success":1,"duration_ms":3179,"item_count":0,"error_count":0,"error_message":null},{"id":113,"fetched_at":"2026-03-25T14:13:18.358707+08:00","success":1,"duration_ms":14350,"item_count":1,"error_count":0,"error_message":null},{"id":112,"fetched_at":"2026-03-25T13:13:18.158850+08:00","success":1,"duration_ms":34381,"item_count":2,"error_count":0,"error_message":null},{"id":111,"fetched_at":"2026-03-25T12:13:20.299118+08:00","success":1,"duration_ms":49266,"item_count":1,"error_count":0,"error_message":null},{"id":110,"fetched_at":"2026-03-25T11:43:20.232479+08:00","success":1,"duration_ms":48419,"item_count":3,"error_count":0,"error_message":null},{"id":109,"fetched_at":"2026-03-25T11:13:19.721320+08:00","success":1,"duration_ms":30395,"item_count":1,"error_count":0,"error_message":null},{"id":108,"fetched_at":"2026-03-25T10:43:18.188204+08:00","success":1,"duration_ms":25885,"item_count":2,"error_count":0,"error_message":null},{"id":107,"fetched_at":"2026-03-25T09:43:18.591841+08:00","success":1,"duration_ms":34839,"item_count":2,"error_count":0,"error_message":null},{"id":106,"fetched_at":"2026-03-25T09:13:18.172512+08:00","success":1,"duration_ms":15371,"item_count":1,"error_count":0,"error_message":null},{"id":105,"fetched_at":"2026-03-25T08:13:19.065204+08:00","success":1,"duration_ms":34558,"item_count":1,"error_count":0,"error_message":null}]},"us10y_reversal":{"latest_sample":{"id":3111,"fetched_at":"2026-03-25T15:34:35.310208+08:00","yield_pct":4.34,"yield_signal":0,"source":"FRED DGS10","note":"10Y: 现值 4.340% / 高点 4.390% / 24.0h回落 5.00bp (阈值 1.00bp)","tenor":"10y"},"latest_samples":{"10y":{"id":3111,"fetched_at":"2026-03-25T15:34:35.310208+08:00","yield_pct":4.34,"yield_signal":0,"source":"FRED DGS10","note":"10Y: 现值 4.340% / 高点 4.390% / 24.0h回落 5.00bp (阈值 1.00bp)","tenor":"10y"}},"recent_runs":[{"id":3118,"fetched_at":"2026-03-25T15:34:35.310208+08:00","success":1,"poll_interval_seconds":60,"duration_ms":2462,"error_message":null,"tenor":"all"},{"id":3117,"fetched_at":"2026-03-25T15:33:35.328745+08:00","success":1,"poll_interval_seconds":60,"duration_ms":2652,"error_message":null,"tenor":"all"},{"id":3116,"fetched_at":"2026-03-25T15:32:35.325977+08:00","success":1,"poll_interval_seconds":60,"duration_ms":3017,"error_message":null,"tenor":"all"},{"id":3115,"fetched_at":"2026-03-25T15:31:35.305444+08:00","success":1,"poll_interval_seconds":60,"duration_ms":2582,"error_message":null,"tenor":"all"},{"id":3114,"fetched_at":"2026-03-25T15:30:35.332958+08:00","success":1,"poll_interval_seconds":60,"duration_ms":2677,"error_message":null,"tenor":"all"},{"id":3113,"fetched_at":"2026-03-25T15:29:35.349975+08:00","success":1,"poll_interval_seconds":60,"duration_ms":2686,"error_message":null,"tenor":"all"},{"id":3112,"fetched_at":"2026-03-25T15:28:35.319658+08:00","success":1,"poll_interval_seconds":60,"duration_ms":2670,"error_message":null,"tenor":"all"},{"id":3111,"fetched_at":"2026-03-25T15:27:35.302113+08:00","success":1,"poll_interval_seconds":60,"duration_ms":2666,"error_message":null,"tenor":"all"},{"id":3110,"fetched_at":"2026-03-25T15:26:35.318787+08:00","success":1,"poll_interval_seconds":60,"duration_ms":2489,"error_message":null,"tenor":"all"},{"id":3109,"fetched_at":"2026-03-25T15:25:35.307535+08:00","success":1,"poll_interval_seconds":60,"duration_ms":3001,"error_message":null,"tenor":"all"}]},"scheduler":{"running":true,"next_run_time":"2026-03-25T15:35:35.089190+08:00","rss_next_run_time":"2026-03-25T15:43:18.119643+08:00","us10y_next_run_time":"2026-03-25T15:35:35.189604+08:00"}}